datawidgets/__init__.py
datawidgets/all.py
datawidgets/class_map.py
datawidgets/exceptions.py
datawidgets/imports.py
datawidgets/interface.py
datawidgets/utils.py
datawidgets/ann/__init__.py
datawidgets/ann/annoy.py
datawidgets/ann/annoy_mixin.py
datawidgets/data/__init__.py
datawidgets/data/abstract.py
datawidgets/data/image.py
datawidgets/data/image_mixins.py
datawidgets/data/mark_mixins.py
datawidgets/dataset/__init__.py
datawidgets/dataset/base_dataset.py
datawidgets/dataset/classification_dataset.py
datawidgets/dataset/dataset_mixins.py
datawidgets/dataset/filtering_mixins.py
datawidgets/dataset/mark_mixins.py
datawidgets/dataset/review_mixins.py
datawidgets/dataset/stats_mixins.py
datawidgets/ui/__init__.py
datawidgets/ui/class_map.py
datawidgets/ui/classification.py
datawidgets/ui/interaction.py
datawidgets/ui/matplotlib.py
datawidgets/ui/style.css
datawidgets/ui/style.py
datawidgets/ui/ui_components.py
tests/__init__.py
tests/conftest.py
tests/data/__init__.py
tests/dataset/__init__.py
tests/dataset/base_dataset_test.py
tests/dataset/mark_mixins_test.py
tests/ui/__init__.py
tests/ui/class_map_test.py
tests/ui/classification_test.py
tests/ui/ui_components_test.py
datawidgets-0.1.2.dist-info/METADATA
datawidgets-0.1.2.dist-info/WHEEL
datawidgets-0.1.2.dist-info/top_level.txt
datawidgets-0.1.2.dist-info/RECORD
